udicti_cli/__init__.py
udicti_cli/main.py
udicti_cli/commands/__init__.py
udicti_cli/commands/dashboard.py
udicti_cli/commands/firebase.py
udicti_cli/commands/github_auth.py
udicti_cli/commands/onboarding.py
udicti_cli/commands/show.py
udicti_cli/commands/welcome.py
udicti_cli-1.0.0.dist-info/licenses/LICENSE
udicti_cli-1.0.0.dist-info/METADATA
udicti_cli-1.0.0.dist-info/WHEEL
udicti_cli-1.0.0.dist-info/entry_points.txt
udicti_cli-1.0.0.dist-info/top_level.txt
udicti_cli-1.0.0.dist-info/RECORD
