Metadata-Version: 2.4
Name: udicti-cli
Version: 1.0.0
Summary: A powerful Github CLI tool to simplify your workflow
Author-email: Sirily <sirilylasway@gmail.com>
License-Expression: MIT
Requires-Python: >=3.11
License-File: LICENSE
Requires-Dist: click>=8.1
Requires-Dist: rich
Requires-Dist: pyfiglet
Requires-Dist: typer[all]
Requires-Dist: requests
Requires-Dist: firebase-admin
Requires-Dist: httpx
Provides-Extra: dev
Requires-Dist: pytest; extra == "dev"
Requires-Dist: black; extra == "dev"
Requires-Dist: ruff; extra == "dev"
Dynamic: license-file
